tasos/apiauth/__init__.py
tasos/apiauth/api/__init__.py
tasos/apiauth/api/base.py
tasos/apiauth/api/group.py
tasos/apiauth/api/permission.py
tasos/apiauth/api/user.py
tasos/apiauth/auth.py
tasos/apiauth/cli.py
tasos/apiauth/config.py
tasos/apiauth/db.py
tasos/apiauth/helpers.py
tasos/apiauth/model.py
tasos/py.typed
tasos_apiauth-0.3.0.dist-info/LICENSE
tasos_apiauth-0.3.0.dist-info/METADATA
tasos_apiauth-0.3.0.dist-info/WHEEL
tasos_apiauth-0.3.0.dist-info/RECORD
