Metadata-Version: 2.1
Name: tasos-apiauth
Version: 0.3.0
Summary: A re-usable FastAPI library that implements authentication, users, groups and permission handling.
Home-page: https://github.com/tristeng/tasos-apiauth
License: MIT
Author: tristeng
Author-email: tristen.georgiou@gmail.com
Requires-Python: >=3.11,<4.0
Classifier: License :: OSI Approved :: MIT License
Classifier: Programming Language :: Python :: 3
Classifier: Programming Language :: Python :: 3.11
Requires-Dist: fastapi (>=0.127,<0.128)
Requires-Dist: pwdlib[argon2] (>=0.3,<0.4)
Requires-Dist: pydantic-settings (>=2.12,<3.0)
Requires-Dist: pydantic[dotenv,email] (>=2.12,<3.0)
Requires-Dist: pyjwt[crypto] (>=2.10,<3.0)
Requires-Dist: python-multipart (==0.0.21)
Requires-Dist: sqlalchemy[asyncio] (>=2.0,<3.0)
Project-URL: Changelog, https://github.com/tristeng/tasos-apiauth/blob/main/CHANGELOG.md
Project-URL: Issues, https://github.com/tristeng/tasos-apiauth/issues
Project-URL: Repository, https://github.com/tristeng/tasos-apiauth.git
